LICENSE
README.md
setup.cfg
setup.py
bad_words_plus/__init__.py
bad_words_plus/__main__.py
bad_words_plus.egg-info/PKG-INFO
bad_words_plus.egg-info/SOURCES.txt
bad_words_plus.egg-info/dependency_links.txt
bad_words_plus.egg-info/top_level.txt