Metadata-Version: 2.1
Name: bad-words-plus
Version: 1.0.0
Summary: Unofficial API for Eksi Sozluk.
Home-page: https://github.com/yusufusta/bad_words_plus
Author: Yusuf Usta
Author-email: yusuf@usta.email
Maintainer: Yusuf Usta
Maintainer-email: yusuf@usta.email
License: GPL3
Keywords: bad words
Platform: UNKNOWN
Classifier: Intended Audience :: Developers
Classifier: License :: OSI Approved :: GNU General Public License v3 (GPLv3)
Classifier: Programming Language :: Python :: 3.6
Classifier: Programming Language :: Python :: 3.7
Classifier: Programming Language :: Python :: 3.8
Classifier: Programming Language :: Python :: 3.9
License-File: LICENSE
